password_policies/__init__.py
password_policies/admin.py
password_policies/apps.py
password_policies/models.py
password_policies/password_validation.py
password_policies/tests.py
password_policies/views.py
password_policies/migrations/__init__.py
django_password_policies_validator-0.0.0.dist-info/LICENSE
django_password_policies_validator-0.0.0.dist-info/METADATA
django_password_policies_validator-0.0.0.dist-info/WHEEL
django_password_policies_validator-0.0.0.dist-info/top_level.txt
django_password_policies_validator-0.0.0.dist-info/RECORD
