Metadata-Version: 2.1
Name: django-password-policies-validator
Version: 0.0.0
Summary: A Django app to validate password complexity and prevent users from reusing previous passwords.
License: BSD 3-Clause License
Project-URL: Homepage, https://github.com/pypa/sampleproject
Keywords: django,password,validator
Classifier: Framework :: Django
Classifier: Programming Language :: Python :: 3
Requires-Python: >=3.8
License-File: LICENSE
